pylsp_black/__init__.py
pylsp_black/plugin.py
python_lsp_black-2.0.0.dist-info/LICENSE
python_lsp_black-2.0.0.dist-info/METADATA
python_lsp_black-2.0.0.dist-info/WHEEL
python_lsp_black-2.0.0.dist-info/entry_points.txt
python_lsp_black-2.0.0.dist-info/top_level.txt
python_lsp_black-2.0.0.dist-info/RECORD
