Metadata-Version: 2.1
Name: python-lsp-black
Version: 2.0.0
Summary: Black plugin for the Python LSP Server
Home-page: https://github.com/python-lsp/python-lsp-black
Author: Python LSP contributors
Author-email: f@fidelramos.net
Project-URL: Bug Tracker, https://github.com/python-lsp/python-lsp-black/issues
Project-URL: Changelog, https://github.com/python-lsp/python-lsp-black/blob/master/CHANGELOG.md
Project-URL: Source Code, https://github.com/python-lsp/python-lsp-black
Classifier: Programming Language :: Python
Classifier: License :: OSI Approved :: MIT License
Classifier: Operating System :: OS Independent
Requires-Python: >=3.8
License-File: LICENSE
Requires-Dist: python-lsp-server>=1.4.0
Requires-Dist: black>=23.11.0
Requires-Dist: tomli; python_version < "3.11"
Provides-Extra: dev
Requires-Dist: isort>=5.0; extra == "dev"
Requires-Dist: flake8; extra == "dev"
Requires-Dist: pre-commit; extra == "dev"
Requires-Dist: pytest; extra == "dev"
Requires-Dist: mypy; extra == "dev"
Requires-Dist: pytest; extra == "dev"
Requires-Dist: types-pkg_resources; extra == "dev"
Requires-Dist: types-setuptools; extra == "dev"
